MANIFEST.in
README.md
setup.cfg
setup.py
gomjabbar/__init__.py
gomjabbar/_version.py
gomjabbar/const.py
gomjabbar/generate.py
gomjabbar.egg-info/PKG-INFO
gomjabbar.egg-info/SOURCES.txt
gomjabbar.egg-info/dependency_links.txt
gomjabbar.egg-info/not-zip-safe
gomjabbar.egg-info/requires.txt
gomjabbar.egg-info/top_level.txt
gomjabbar/data/alloc.c.jinja
gomjabbar/data/connections.c.jinja
gomjabbar/data/macros.c
gomjabbar/data/params.c.jinja
gomjabbar/ifs/__init__.py
gomjabbar/ifs/ast.py
gomjabbar/ifs/build.py
gomjabbar/ifs/lexer.py
gomjabbar/ifs/parser.py
gomjabbar/ifs/tables/__init__.py